tecton_utils/__init__.py
tecton_utils/checkpoint.py
tecton_utils/core_utils.py
tecton_utils/realtime_utils.py
tecton_utils/utils.py
tecton_utils/ai/__init__.py
tecton_utils/ai/_utils.py
tecton_utils/ai/client.py
tecton_utils/ai/deco.py
tecton_utils/ai/service.py
tecton_utils/testing/__init__.py
tecton_utils/testing/fixtures.py
tecton_utils/testing/mocks.py
tecton_utils-0.0.3.dist-info/METADATA
tecton_utils-0.0.3.dist-info/WHEEL
tecton_utils-0.0.3.dist-info/entry_points.txt
tecton_utils-0.0.3.dist-info/RECORD
